bencode_rs/__init__.py
bencode_rs/bencode_rs.cp314-win_amd64.pyd
bencode_rust-0.1.0.dist-info/METADATA
bencode_rust-0.1.0.dist-info/WHEEL
bencode_rust-0.1.0.dist-info/RECORD
