Metadata-Version: 2.4
Name: bencode_rust
Version: 0.1.0
Classifier: Programming Language :: Rust
Classifier: Programming Language :: Python :: Implementation :: CPython
Classifier: Programming Language :: Python :: Implementation :: PyPy
Summary: A modern bencode parser written from scratch for the next generation of torrent streaming
Requires-Python: >=3.10
